vinkesh_sdk/__init__.py
vinkesh_sdk/api_client.py
vinkesh_sdk/api_response.py
vinkesh_sdk/configuration.py
vinkesh_sdk/exceptions.py
vinkesh_sdk/py.typed
vinkesh_sdk/rest.py
vinkesh_sdk/api/__init__.py
vinkesh_sdk/api/pet_api.py
vinkesh_sdk/api/store_api.py
vinkesh_sdk/api/user_api.py
vinkesh_sdk/models/__init__.py
vinkesh_sdk/models/address.py
vinkesh_sdk/models/api_response.py
vinkesh_sdk/models/category.py
vinkesh_sdk/models/customer.py
vinkesh_sdk/models/order.py
vinkesh_sdk/models/pet.py
vinkesh_sdk/models/tag.py
vinkesh_sdk/models/user.py
vinkesh_sdk-1.0.0.dist-info/METADATA
vinkesh_sdk-1.0.0.dist-info/WHEEL
vinkesh_sdk-1.0.0.dist-info/top_level.txt
vinkesh_sdk-1.0.0.dist-info/RECORD
